tffs/__init__.py
tffs/app.py
tfffs-1.1.0.dist-info/LICENSE
tfffs-1.1.0.dist-info/METADATA
tfffs-1.1.0.dist-info/WHEEL
tfffs-1.1.0.dist-info/top_level.txt
tfffs-1.1.0.dist-info/RECORD
