Metadata-Version: 2.2
Name: tfffs
Version: 1.1.0
Summary: Feature selection based on top frequency
Home-page: https://github.com/VuKieuAnh/TFFS
Author: Vu Kieu Anh
Author-email: vukieuanh.hnue@gmail.com
Classifier: Programming Language :: Python :: 3
Classifier: License :: OSI Approved :: MIT License
Classifier: Operating System :: OS Independent
Requires-Python: >=3.6
License-File: LICENSE
Dynamic: author
Dynamic: author-email
Dynamic: classifier
Dynamic: home-page
Dynamic: requires-python
Dynamic: summary
